fwd/__init__.py
fwd/_version.py
fwd/fwd.py
fwd/cli/.gitkeep
fwd/cli/fwd.py
fwd/data/.gitkeep
fwd/data/emacs-logo/emacs-128x128.png
fwd/data/emacs-logo/emacs.svg
fwd/tests/__init__.py
fwd/tests/test_fwd.py
fwd-0.1.1.dist-info/AUTHORS.rst
fwd-0.1.1.dist-info/LICENSE
fwd-0.1.1.dist-info/METADATA
fwd-0.1.1.dist-info/WHEEL
fwd-0.1.1.dist-info/entry_points.txt
fwd-0.1.1.dist-info/top_level.txt
fwd-0.1.1.dist-info/RECORD
